pyil_bin.py
pyil_bin-0.1.dist-info/LICENSE
pyil_bin-0.1.dist-info/METADATA
pyil_bin-0.1.dist-info/WHEEL
pyil_bin-0.1.dist-info/entry_points.txt
pyil_bin-0.1.dist-info/top_level.txt
pyil_bin-0.1.dist-info/RECORD
