Metadata-Version: 2.1
Name: pyil-bin
Version: 0.1
Summary: Embed python expressions in bash
Home-page: https://gitlab.com/qwolphin/pyil
Author: Lumi Akimova
Author-email: q@wolph.in
Classifier: Intended Audience :: Developers
Classifier: Natural Language :: English
Classifier: License :: OSI Approved :: MIT License
Classifier: Programming Language :: Python
Classifier: Programming Language :: Python :: 3
License-File: LICENSE
